LunarAI/__init__.py
LunarAI/model.py
LunarAI/activations/__init__.py
LunarAI/activations/activations.py
LunarAI/activations/dadz.py
LunarAI/activations/functions.py
LunarAI/ai_libs/__init__.py
LunarAI/ai_libs/array_type.py
LunarAI/ai_libs/matrix.py
LunarAI/examples/__init__.py
LunarAI/examples/example_1.py
LunarAI/layers/__init__.py
LunarAI/layers/embedding.py
LunarAI/layers/layer.py
LunarAI/layers/self_attention_layer.py
LunarAI/loss/__init__.py
LunarAI/loss/deda.py
LunarAI/loss/functions.py
LunarAI/loss/loss.py
LunarAI/train/__init__.py
LunarAI/train/sgd.py
LunarAI-0.0.3.dist-info/METADATA
LunarAI-0.0.3.dist-info/WHEEL
LunarAI-0.0.3.dist-info/top_level.txt
LunarAI-0.0.3.dist-info/RECORD
